sdlm/__init__.py
sdlm/main.py
sdlm-0.3.dist-info/LICENSE
sdlm-0.3.dist-info/METADATA
sdlm-0.3.dist-info/WHEEL
sdlm-0.3.dist-info/entry_points.txt
sdlm-0.3.dist-info/top_level.txt
sdlm-0.3.dist-info/RECORD
