Metadata-Version: 2.1
Name: sdlm
Version: 0.3
License-File: LICENSE
Requires-Dist: requests>=2.32.3
Requires-Dist: bs4>=0.0.2
